alfred/__init__.py
alfred/alfred.py
alfred/modules/__init__.py
alfred/modules/scrap/__init__.py
alfred/modules/scrap/image_scraper.py
alfred/modules/scrap/scraper_images.py
alfred/modules/text/__init__.py
alfred/modules/vision/__init__.py
alfred/modules/vision/video_extractor.py
alfred_py-0.1.1.dist-info/DESCRIPTION.rst
alfred_py-0.1.1.dist-info/METADATA
alfred_py-0.1.1.dist-info/RECORD
alfred_py-0.1.1.dist-info/WHEEL
alfred_py-0.1.1.dist-info/entry_points.txt
alfred_py-0.1.1.dist-info/metadata.json
alfred_py-0.1.1.dist-info/top_level.txt
