Metadata-Version: 2.0
Name: alfred-py
Version: 0.1.1
Summary: alfred is a deep learning scripts helper, built with many standby functions for process image or text
Home-page: https://github.com/jinfagang/alfred
Author: Lucas Jin
Author-email: jinfagang10@163.com
License: GPL
Keywords: deep learning,script helper,tools
Platform: any
Requires-Dist: colorama
Requires-Dist: opencv-python
Requires-Dist: requests
